SCPLibrary/__init__.py
SCPLibrary/_version.py
SCPLibrary/library.py
robotframework_scplibrary-1.2.0.dist-info/METADATA
robotframework_scplibrary-1.2.0.dist-info/RECORD
robotframework_scplibrary-1.2.0.dist-info/WHEEL
robotframework_scplibrary-1.2.0.dist-info/top_level.txt
