Metadata-Version: 1.1
Name: robotframework-scplibrary
Version: 1.2.0
Summary: Robot Framework test library for transferring files via Secure Copy (SCP)
Home-page: https://www.tylercrumpton.com
Author: Tyler Crumpton
Author-email: tyler.crumpton@gmail.com
License: GPLv3
Download-URL: https://github.com/tylercrumpton/robotframework-scplibrary
Project-URL: Bug Reports, https://github.com/tylercrumpton/robotframework-scplibrary/issues
Project-URL: Source, https://github.com/tylercrumpton/robotframework-scplibrary
Platform: UNKNOWN
